{
    "fluentMethods": true,
    "relationships": [],
    "fields": [
        {
            "fieldName": "comment",
            "fieldType": "String",
            "fieldValidateRules": [
                "required",
                "maxlength"
            ],
            "fieldValidateRulesMaxlength": "255"
        },
        {
            "fieldName": "createdOn",
            "fieldType": "ZonedDateTime"
        },
        {
            "fieldName": "updatedOn",
            "fieldType": "ZonedDateTime"
        },
        {
            "fieldName": "jobId",
            "fieldType": "Long",
            "fieldValidateRules": [
                "required"
            ]
        }
    ],
    "changelogDate": "20170202112822",
    "dto": "no",
    "service": "serviceImpl",
    "entityTableName": "job_status",
    "pagination": "no"
}
